{"assets":{"162C7708CEE0F218142383F4CBAF5E38":{"type":"texture","index":0,"assetRequest":{"type":"slide","state":"outgoing","slide":"BE3DB358-C929-4D34-AA61-2E816B3734A9"},"url":{"web":"assets/BE3DB358-C929-4D34-AA61-2E816B3734A9.svgmap"},"width":1024,"height":768},"69E244A8E99E54E7EF126062BAC60ED4":{"type":"texture","index":1,"assetRequest":{"type":"slide","state":"incoming","slide":"3627AA7B-3375-4143-B964-950AD9C6A57F"},"url":{"web":"assets/BE3DB358-C929-4D34-AA61-2E816B3734A9.svgmap"},"width":1024,"height":768}},"events":[{"effects":[{"beginTime":0,"baseLayer":{"animations":[],"initialState":{"affineTransform":[1,0,0,1,0,0],"masksToBounds":false,"rotation":0,"scale":1,"position":{"pointX":512,"pointY":384},"width":1024,"sublayerTransform":[1,0,0,0,0,1,0,0,0,0,1,0,0,0,0,1],"contentsRect":{"y":0,"x":0,"width":1,"height":1},"opacity":1,"edgeAntialiasingMask":251658240,"height":768,"hidden":false,"anchorPoint":{"pointX":0.5,"pointY":0.5}},"objectID":"0","layers":[{"animations":[],"initialState":{"affineTransform":[1,0,0,1,0,0],"masksToBounds":false,"rotation":0,"scale":1,"position":{"pointX":512,"pointY":384},"width":1024,"sublayerTransform":[1,0,0,0,0,1,0,0,0,0,1,-0.0004922987690640373,0,0,0,1],"contentsRect":{"y":0,"x":0,"width":1,"height":1},"opacity":1,"edgeAntialiasingMask":251658240,"height":768,"hidden":false,"anchorPoint":{"pointX":0.5,"pointY":0.5}},"layers":[{"animations":[],"layers":[],"texturedRectangle":{"isBackgroundTexture":false,"singleTextureOpacity":1,"textureType":0,"textBaseline":0,"textXHeight":0,"isVerticalText":false},"initialState":{"affineTransform":[1,0,0,1,0,0],"masksToBounds":false,"rotation":0,"scale":1,"position":{"pointX":512,"pointY":384},"width":1024,"sublayerTransform":[1,0,0,0,0,1,0,0,0,0,1,0,0,0,0,1],"contentsRect":{"y":0,"x":0,"width":1,"height":1},"opacity":1,"edgeAntialiasingMask":0,"height":768,"hidden":false,"anchorPoint":{"pointX":0.5,"pointY":0.5}},"texture":"69E244A8E99E54E7EF126062BAC60ED4"},{"animations":[{"timeOffset":0,"from":{"scalar":false},"beginTime":0,"repeatCount":0,"fillMode":"both","property":"hidden","autoreverses":false,"duration":0.01,"to":{"scalar":true}}],"layers":[],"texturedRectangle":{"isBackgroundTexture":false,"singleTextureOpacity":1,"textureType":0,"textBaseline":0,"textXHeight":0,"isVerticalText":false},"initialState":{"affineTransform":[1,0,0,1,0,0],"masksToBounds":false,"rotation":0,"scale":1,"position":{"pointX":512,"pointY":384},"width":1024,"sublayerTransform":[1,0,0,0,0,1,0,0,0,0,1,0,0,0,0,1],"contentsRect":{"y":0,"x":0,"width":1,"height":1},"opacity":1,"edgeAntialiasingMask":0,"height":768,"hidden":false,"anchorPoint":{"pointX":0.5,"pointY":0.5}},"texture":"162C7708CEE0F218142383F4CBAF5E38"}]}]},"effects":[],"duration":0.01,"type":"transition","name":"none","objectID":"0"}],"automaticPlay":false,"hyperlinks":[{"url":"https://fetch.spec.whatwg.org/#block-bad-port","targetRectangle":{"y":485.9600048065186,"x":393.1900815852186,"width":539.1878400000002,"height":61.24000120162964}}],"accessibility":[{"text":"Potential future steps in n WebKit (2/2)","targetRectangle":{"y":40,"x":133.4959999999999,"width":775.6896000000002,"height":160}},{"text":"Update memory cache model to be closer to fetch model","targetRectangle":{"y":210,"x":104.2000015852186,"width":663.1113600000001,"height":31}},{"text":"Fetched resource model is origin/fetch-mode specific","targetRectangle":{"y":241,"x":139.2000015852186,"width":618.4771200000001,"height":61.24000120162964}},{"text":"Tame the navigation resource loading path","targetRectangle":{"y":302.2400012016296,"x":104.2000015852186,"width":493.2057600000001,"height":61.24000120162964}},{"text":"Not as straightforward as sub-resource loading","targetRectangle":{"y":363.4800024032593,"x":139.2000015852186,"width":544.50144,"height":61.24000120162964}},{"text":"Check/fix low-level network details","targetRectangle":{"y":424.7200036048889,"x":104.2000015852186,"width":397.53504,"height":61.24000120162964}},{"text":"Which ports to block (https://fetch.spec.whatwg.org/#block-bad-port)","targetRectangle":{"y":485.9600048065186,"x":139.2000015852186,"width":801.8092800000002,"height":61.24000120162964}},{"text":"Time of browser-controlled header insertion","targetRectangle":{"y":547.2000060081482,"x":139.2000015852186,"width":502.2518399999999,"height":61.24000120162964}},{"text":"HTTP response trailer","targetRectangle":{"y":608.4400072097778,"x":139.2000015852186,"width":250.15392,"height":61.24000120162964}},{"text":"Redirection number","targetRectangle":{"y":669.6800084114075,"x":139.2000015852186,"width":228.56256,"height":61.24000120162964}}],"baseLayer":{"animations":[],"initialState":{"affineTransform":[1,0,0,1,0,0],"masksToBounds":false,"rotation":0,"scale":1,"position":{"pointX":512,"pointY":384},"width":1024,"sublayerTransform":[1,0,0,0,0,1,0,0,0,0,1,0,0,0,0,1],"contentsRect":{"y":0,"x":0,"width":1,"height":1},"opacity":1,"edgeAntialiasingMask":251658240,"height":768,"hidden":false,"anchorPoint":{"pointX":0.5,"pointY":0.5}},"objectID":"0","layers":[{"animations":[],"initialState":{"affineTransform":[1,0,0,1,0,0],"masksToBounds":false,"rotation":0,"scale":1,"position":{"pointX":512,"pointY":384},"width":1024,"sublayerTransform":[1,0,0,0,0,1,0,0,0,0,1,-0.0004922987690640373,0,0,0,1],"contentsRect":{"y":0,"x":0,"width":1,"height":1},"opacity":1,"edgeAntialiasingMask":251658240,"height":768,"hidden":false,"anchorPoint":{"pointX":0.5,"pointY":0.5}},"layers":[{"animations":[],"layers":[],"texturedRectangle":{"isBackgroundTexture":false,"singleTextureOpacity":1,"textureType":0,"textBaseline":0,"textXHeight":0,"isVerticalText":false},"initialState":{"affineTransform":[1,0,0,1,0,0],"masksToBounds":false,"rotation":0,"scale":1,"position":{"pointX":512,"pointY":384},"width":1024,"sublayerTransform":[1,0,0,0,0,1,0,0,0,0,1,0,0,0,0,1],"contentsRect":{"y":0,"x":0,"width":1,"height":1},"opacity":1,"edgeAntialiasingMask":0,"height":768,"hidden":false,"anchorPoint":{"pointX":0.5,"pointY":0.5}},"texture":"162C7708CEE0F218142383F4CBAF5E38"}]}]}}]}